package_name/__init__.py
package_name/cli.py
package_medium_post-1.1.0.dist-info/LICENSE
package_medium_post-1.1.0.dist-info/METADATA
package_medium_post-1.1.0.dist-info/WHEEL
package_medium_post-1.1.0.dist-info/entry_points.txt
package_medium_post-1.1.0.dist-info/top_level.txt
package_medium_post-1.1.0.dist-info/RECORD
