Metadata-Version: 2.1
Name: package-medium-post
Version: 1.1.0
Summary: prints time in command.
Home-page: https://github.com/RonsenbergVI/cicd_circleci_codeclimate.git
Author: Rene-Jean Corneille
Author-email: corneille.r.j@gmail.com
License: MIT
Platform: UNKNOWN
Classifier: License :: OSI Approved :: MIT License
Classifier: Programming Language :: Python :: 3
Classifier: Programming Language :: Python :: 3.7
Requires-Dist: Click
